[{"title":"I love checkers","userName":"Inturi","timeCommented":"2021-09-16T18:39:59.790Z","comments":"Web Arcade is awesome","gameId":1},{"title":"Can play hours","userName":"Rohdes","timeCommented":"2021-09-16T19:02:07.308Z","comments":"I played this game whole day non-stop on a Sunday!","gameId":1},{"title":"Weekend fun","userName":"Yabaluru","timeCommented":"2021-09-17T17:05:36.162Z","comments":"Like to play board games over the weekends with family!","gameId":1},{"title":"Checkers, I love it","userName":"John","timeCommented":"2021-09-19T12:25:11.930Z","comments":"This is an awesome game.","gameId":1},{"title":"test","userName":"test","timeCommented":"2021-09-19T16:32:18.719Z","comments":"test","gameId":1},{"title":"test2","userName":"tes2","timeCommented":"2021-09-19T16:58:19.018Z","comments":"test2","gameId":1},{"title":"test3","userName":"test3","timeCommented":"2021-09-19T21:48:09.368Z","comments":"test3","gameId":1},{"title":"test3","userName":"test3","timeCommented":"2021-09-19T21:49:09.262Z","comments":"test3","gameId":1},{"title":"test","userName":"Snippets in Google Chrome","timeCommented":"2021-09-19T21:49:43.324Z","comments":"test","gameId":1},{"title":"test","userName":"Snippets in Google Chrome","timeCommented":"2021-09-19T21:50:46.958Z","comments":"test","gameId":1},{"title":"test","userName":"Snippets in Google Chrome","timeCommented":"2021-09-19T21:52:15.308Z","comments":"test","gameId":1},{"title":"test","userName":"Snippets in Google Chrome","timeCommented":"2021-09-19T21:56:46.236Z","comments":"test","gameId":1},{"title":"test","userName":"Working with Yarn Global Commands","timeCommented":"2021-09-19T22:32:34.949Z","comments":"test","gameId":1},{"title":"test","userName":"Working with Yarn Global Commands","timeCommented":"2021-09-20T10:05:51.443Z","comments":"test","gameId":1}]